<smile><item><content>本人发表说说：如果可以，我给我未来的丈母娘给差评，发货速度太慢了！&lt;br&gt;看到第一条评论：亲，你付款了吗？&lt;br&gt;</content></item><item><content>那年雪特别大，一天，去表哥家玩，表哥问我，想去堆雪人么？我当然满口答应了。&lt;br&gt;然后他带着我走到一颗大树下，然后对我说，站着别动，&lt;br&gt;然后他一脚踹在树上，然后飞快的跑开了，然后我特么站在树下成了一个雪人。。。&lt;br&gt;</content></item><item><content>早上在路边摊吃混沌，小摊桌子上一个红茶瓶子，误以为是醋，倒了一点后感觉不够酸，又倒了一点还是不够酸，又倒，又倒，又倒……&lt;br&gt;后来大喊，老板，你的醋怎么不酸啊！&lt;br&gt;老板走过来说：咦！这不刚才那位客人剩的红茶么？&lt;br&gt;瞬间脸都绿了……&lt;br&gt;</content></item><item><content>今天内急让我出了洋相。好不容易等到地铁到站，我顾不上什么绅士风度，三步并作两步地挤下车朝厕所奔去。&lt;br&gt;结果，我走到厕所门口时发现大事不妙，一个“正在维修，请稍候”的牌子竖在我面前。这要等到什么时候呀？&lt;br&gt;我忍，我再忍。十几分钟后，一个工人走过来拿起牌子就走，嘴里还嘟哝着：“一直找不到，原来丢在这里了。”&lt;br&gt;</content></item><item><content>正在杀只豆腐，请问豆腐脑在哪个位置？挺急的，在线等。&lt;br&gt;</content></item><item><content>“沙师弟，行李呢？”&lt;br&gt;“被抢了”&lt;br&gt;“师父的白龙马呢？”&lt;br&gt;“也被枪了”&lt;br&gt;“何方妖怪竟然敢抢到俺老孙的头上来！”&lt;br&gt;“他们说是市容管理处的”&lt;br&gt;“城管。。。”&lt;br&gt;</content></item><item><content>司马迁写《史记》时写了不少汉武帝的坏话，汉武帝就问他：“你就不怕死吗？”&lt;br&gt;司马迁回答：“皇上听过愚公移山吗？我死了还有我儿子，我儿子死了还有我孙子，子子孙孙无穷尽也！”&lt;br&gt;然后。。。然后司马迁就被宫刑了。&lt;br&gt;</content></item><item><content>“我的父亲走丢了，能在电视上登个寻人启事吗？”&lt;br&gt;“可以，各时段价钱不一样，你整啥价位的？”&lt;br&gt;“咋还要钱呢？你们不是有个节目叫爸爸去哪儿吗？”&lt;br&gt;</content></item><item><content>某地发生了一些怪事，最近一个月的新生婴儿几乎都不吃母乳，而且面对母亲乳房时会出现焦虑不安的反应，这到底是怎么回事呢？！&lt;br&gt;后来科学家苦心研究，发明了一种可以读懂人内心想法的仪器！！&lt;br&gt;婴儿带上了仪器！果然功夫不负有心人，人们终于找到了病因。。。&lt;br&gt;因为这些婴儿都是天秤座，他们面对乳头都在考虑着：我该吃哪边比较好呢？&lt;br&gt;</content></item><item><content>昨晚，儿子见我吃药，问：“妈妈，你怎么了？”&lt;br&gt;答：“感冒了”&lt;br&gt;又问：“怎么感冒了？”&lt;br&gt;答：“被你气的！”&lt;br&gt;儿子：“那你应该吐血才对啊！”&lt;br&gt;</content></item></smile>