<smile><item><content>老婆問我：如果有女同事勾引你你會順從嗎？我笑著搖了搖頭，呵呵，把我當成什麼人了？我是那種會告訴你真實想法的人嗎？</content></item><item><content>學生：老師人才是什麼？&lt;br&gt;老師：人才就是把社會上的所有人聚在一起，反覆提煉，鍛造，壓榨。剩下的就是人才了。&lt;br&gt;學生：哦……那不是人渣嗎？</content></item><item><content>能讓同桌在你上課玩手機時，認認真真幫你把風的方法只有一個：那就是玩他的手機。</content></item><item><content>同學A：“你為什麼這麼努力學習？”&lt;br&gt;B：“因為我太愛我女朋友了。”&lt;br&gt;A：“就因為這個？”&lt;br&gt;B：“我女朋友是個吃貨，我害怕她以後吃不到好吃的。”</content></item><item><content>學長：“你是大一的吧？”&lt;br&gt;學姐：“哦，我大三的。”&lt;br&gt;學長：“看你皮膚，還以為你剛軍訓完。。。”</content></item><item><content>彩票是一種“低智商稅”。 </content></item><item><content>床是夢的溫柔鄉，也是夢想的棺材盒。</content></item><item><content>錢財你已經擁有一半了。──賤。</content></item><item><content>悲觀的人看前面都是紅燈，樂觀的人看前面都是綠燈，可是智者呢，就是色盲。</content></item><item><content>大家捧你時你是個玻璃杯子，大家鬆手時你就是個玻璃茬子。 </content></item></smile>